visu/CalculTraj.py
visu/InputElectrons.py
visu/Win3D.py
visu/WinCut.py
visu/WinOption.py
visu/WinPreference.py
visu/__init__.py
visu/aboutWindows.py
visu/andor.py
visu/confVisu.ini
visu/defaultTrajectory.ini
visu/default_values.ini
visu/moteurRSAI.py
visu/moteurRSAIFDB.py
visu/pysifreader.py
visu/sifreader.py
visu/visual.py
visu/visualElectrons.py
visu/visualLight.py
visu/visual_old.py
visu/winCrop.py
visu/winFFT.py
visu/winHist.py
visu/winMath.py
visu/winMeas.py
visu/winPointing.py
visu/winSpectro.py
visu/winSuppE.py
visu/winZoom.py
visu/winspec.py
visu/icons/Capture decran 2020-03-23 a 09.50.40.png
visu/icons/Capture d’écran 2020-03-23 à 09.50.40.png
visu/icons/LOA.png
visu/icons/Open.png
visu/icons/Open.svg
visu/icons/Red_circle.png
visu/icons/Saving.png
visu/icons/Saving.svg
visu/icons/Settings.png
visu/icons/Settings.svg
visu/icons/Stop.png
visu/icons/Stop.svg
visu/icons/Toggle_Off.png
visu/icons/Toggle_Off.svg
visu/icons/Toggle_On.png
visu/icons/Toggle_On.svg
visu/icons/analytics.png
visu/icons/briefcase.png
visu/icons/calendar.png
visu/icons/check-mark.png
visu/icons/circleGray.png
visu/icons/circular-arrows.png
visu/icons/coin.png
visu/icons/colors-icon.png
visu/icons/colourBar.png
visu/icons/crayons.png
visu/icons/data1.png
visu/icons/data2.png
visu/icons/diskette.png
visu/icons/disketteAuto.png
visu/icons/disketteSave.png
visu/icons/download.png
visu/icons/expand.png
visu/icons/eye.svg
visu/icons/fliphorizontal.png
visu/icons/flipvertical.png
visu/icons/hide.svg
visu/icons/laptop.png
visu/icons/light-bulb.png
visu/icons/ligne.jpeg
visu/icons/line-chart.png
visu/icons/line.png
visu/icons/loupe.png
visu/icons/math.png
visu/icons/minimize.png
visu/icons/more.png
visu/icons/padlock.png
visu/icons/pentagon.png
visu/icons/pref.png
visu/icons/rectangle.png
visu/icons/recycle.png
visu/icons/resize.png
visu/icons/robotics.png
visu/icons/saveAuto.png
visu/icons/saveAutoOn.png
visu/icons/search.png
visu/icons/send.png
visu/icons/shield.png
visu/icons/target.png
visu-2024.4.dist-info/METADATA
visu-2024.4.dist-info/WHEEL
visu-2024.4.dist-info/top_level.txt
visu-2024.4.dist-info/RECORD
