Metadata-Version: 2.1
Name: visu
Version: 2024.4
Summary: Data visualization
Home-page: https://github.com/julienGautier77/visu
Author: Julien Gautier
Author-email: julien.gautier@ensta.fr
Classifier: Programming Language :: Python :: 3
Classifier: License :: Free for non-commercial use
Classifier: Operating System :: OS Independent
Classifier: Topic :: Scientific/Engineering :: Visualization
Requires-Dist: matplotlib
Requires-Dist: PyQt6-sip ==13.5.2
Requires-Dist: PyQt6-qt6 ==6.5.1
Requires-Dist: PyQt6 ==6.5.1
Requires-Dist: qdarkstyle
Requires-Dist: pyqtgraph
Requires-Dist: scipy
Requires-Dist: six
